{
  "id": "flip-board-green",
  "name": "Folding Board — Green",
  "category": "flip",
  "tags": [
    "fold",
    "plane",
    "3d",
    "theme",
    "green"
  ],
  "tech": "css",
  "framework": "none",
  "dependencies": [],
  "variables": {
    "--lc-size": "40px",
    "--lc-color": "#22c55e",
    "--lc-speed": "2.4s"
  },
  "source": {
    "name": "Loading Companion",
    "url": "https://github.com/loading-companion",
    "author": "Loading Companion"
  },
  "license": "MIT",
  "copyright": null,
  "generated": true,
  "baseId": "flip-board"
}
