{
  "id": "ripple-triple-cyan",
  "name": "Triple Ripple — Cyan",
  "category": "ripple",
  "tags": [
    "ripple",
    "rings",
    "expand",
    "theme",
    "cyan"
  ],
  "tech": "css",
  "framework": "none",
  "dependencies": [],
  "variables": {
    "--lc-size": "60px",
    "--lc-color": "#06b6d4",
    "--lc-speed": "2s"
  },
  "source": {
    "name": "Loading Companion",
    "url": "https://github.com/loading-companion",
    "author": "Loading Companion"
  },
  "license": "MIT",
  "copyright": null,
  "generated": true,
  "baseId": "ripple-triple"
}
