{
  "id": "whirl-dominoes-teal",
  "name": "Dominoes — Teal",
  "category": "bars",
  "tags": [
    "dominoes",
    "fall",
    "rotate",
    "theme",
    "teal"
  ],
  "tech": "css",
  "framework": "none",
  "dependencies": [],
  "variables": {
    "--lc-color": "#14b8a6",
    "--lc-speed": "1.6s"
  },
  "source": {
    "name": "Whirl",
    "url": "https://github.com/jh3y/whirl",
    "author": "Jhey Tompkins"
  },
  "license": "MIT",
  "copyright": "Copyright (c) 2019 Jhey Tompkins",
  "generated": true,
  "baseId": "whirl-dominoes"
}
