{
  "id": "svg-pulse-dots-violet",
  "name": "SVG Pulse Dots — Violet",
  "category": "svg",
  "tags": [
    "dots",
    "pulse",
    "scale",
    "theme",
    "violet"
  ],
  "tech": "svg",
  "framework": "none",
  "dependencies": [],
  "variables": {
    "--lc-size": "60px",
    "--lc-color": "#8b5cf6",
    "--lc-speed": "1s"
  },
  "source": {
    "name": "Loading Companion",
    "url": "https://github.com/loading-companion",
    "author": "Loading Companion"
  },
  "license": "MIT",
  "copyright": null,
  "generated": true,
  "baseId": "svg-pulse-dots"
}
