{
  "id": "svgl-oval-rose",
  "name": "SVG Oval — Rose",
  "category": "spinner",
  "tags": [
    "ring",
    "rotate",
    "oval",
    "theme",
    "rose"
  ],
  "tech": "svg",
  "framework": "none",
  "dependencies": [],
  "variables": {
    "--lc-size": "40px",
    "--lc-color": "#f43f5e"
  },
  "source": {
    "name": "SVG Loaders",
    "url": "https://github.com/SamHerbert/SVG-Loaders",
    "author": "Sam Herbert"
  },
  "license": "MIT",
  "copyright": "Copyright (c) 2014 Sam Herbert",
  "generated": true,
  "baseId": "svgl-oval"
}
